src/I2S_shift_register.v
module shift_register(
	input clk,
	input [31:0] sample_left,
	input [31:0] sample_right,
	input [3:0] sample_size,
	input start,
	input rst,
	output reg busy_right,
	output reg busy_left,
	output word_select,
	output reg data_out,
	output reg clk_out
	);
	
	parameter IDLE_s=0, START_s=1, RUNNING_s=3;
	parameter S_8BIT=0, S_12BIT=1, S_16BIT=3, S_32BIT=4;
	parameter LEFT=0, RIGHT=1;
	
	reg [7:0] sample_left_r;
	reg [7:0] sample_right_r;
	reg [3:0] state;
	reg [3:0] next_state;
	reg [7:0] bit_counter_right;
	reg [7:0] bit_counter_left;
	reg [7:0] counter_size;
	reg current_out;
	
	assign word_select = current_out;
	
	always @ (posedge clk) begin
		case(sample_size)
				S_8BIT  : counter_size <= 8'd8;
				S_12BIT : counter_size <= 8'd12;
				S_16BIT : counter_size <= 8'd16;
				S_32BIT : counter_size <= 8'd32;
			endcase
		end
	
	always @ (posedge clk) begin
		if(rst) begin
			state       <= IDLE_s;
		end
		else
			state       <= next_state;
	end
	
	always @(*) begin
		case (state)
			IDLE_s:
				if(start)
					next_state = START_s;
				else
					next_state = IDLE_s;
			START_s:
				next_state = RUNNING_s;
			RUNNING_s:
				next_state = RUNNING_s;
			default:
				next_state  = IDLE_s;
		endcase
	end
	
	
	
	always @ (posedge clk) begin
		if(rst) begin
		sample_left_r <= 0;
		sample_right_r <= 0;
		busy_right <= 0;
		busy_left <= 0;
//		word_select <= 0;
		data_out <= 0;
		clk_out <= 0;
		current_out <= 0;
		end
		
		else if(state == START_s) begin
			sample_left_r <= sample_left;
			sample_right_r <= sample_right;
			
			bit_counter_right <= counter_size+1;
			bit_counter_left <= counter_size+1;
		end
		
		else if(state == RUNNING_s) begin
		
			if(current_out == LEFT) begin
				if(bit_counter_left != 0) begin
				//shift bit to output
					data_out <= sample_left_r[0];
					sample_left_r <= sample_left_r >> 1;
					bit_counter_left--;
				end
				else begin
					current_out <= RIGHT;
					bit_counter_left <= counter_size;
				end
			end
			else if(current_out == RIGHT) begin
				if(bit_counter_right != 0) begin
				//shift bit to output
					data_out <= sample_right_r[0];
					sample_right_r <= sample_right_r >> 1;
					bit_counter_right--;
				end
				else begin
					current_out <= LEFT;
					bit_counter_right <= counter_size;
				end
				
			end
		
		end
		
		
	end
	
	
	
endmodule

src/I2S_shift_register_tb.v
`timescale 1ns / 1ps

module I2S_shift_register_tb;
	parameter S_8BIT=0, S_12BIT=1, S_16BIT=3, S_32BIT=4;
	parameter SAMPLE_LEFT_VALUE = 145;
	parameter SAMPLE_RIGHT_VALUE = 145;
	parameter SAMPLE_SIZE_VALUE = S_8BIT;

	reg CLK;
	reg START;
	reg RST;
	reg [32:0] SAMPLE_LEFT;
	reg [32:0] SAMPLE_RIGHT;
	reg [3:0] SAMPLE_SIZE;
	wire WORD_SELECT;
	wire DATA_OUT;

	shift_register uut(
		.clk(CLK),
		.sample_left(SAMPLE_LEFT),
		.sample_right(SAMPLE_RIGHT),
		.sample_size(SAMPLE_SIZE),
		.start(START),
		.rst(RST),
		//.busy_right(),
		//.busy_left(),
		.word_select(WORD_SELECT),
		.data_out(DATA_OUT)
		//.clk_out()
		
	);

	
	initial begin
		$dumpfile("I2S_shift_register_test.vcd");
		$dumpvars();
		CLK = 0;
		START = 0;
		RST = 0;
		SAMPLE_LEFT = SAMPLE_LEFT_VALUE;
		SAMPLE_RIGHT = SAMPLE_RIGHT_VALUE;
		SAMPLE_SIZE = SAMPLE_SIZE_VALUE;
	end
	
	initial begin
		wait(!CLK);
		#1
		RST = 1;
		#3
		RST = 0;
		
		wait(!CLK);
		#1
		START = 1;
		#3
		START = 0;
		
	end
	
	
	
	initial begin
        #3000 $finish;
    end

    always
        #2  CLK =  ! CLK;

endmodule

src/I2S_shift_register_test.vcd
$date
	Tue Aug 25 01:19:29 2020
$end
$version
	Icarus Verilog
$end
$timescale
	1ps
$end
$scope module I2S_shift_register_tb $end
$var wire 1 ! WORD_SELECT $end
$var wire 1 " DATA_OUT $end
$var reg 1 # CLK $end
$var reg 1 $ RST $end
$var reg 33 % SAMPLE_LEFT [32:0] $end
$var reg 33 & SAMPLE_RIGHT [32:0] $end
$var reg 4 ' SAMPLE_SIZE [3:0] $end
$var reg 1 ( START $end
$scope module uut $end
$var wire 1 # clk $end
$var wire 1 $ rst $end
$var wire 32 ) sample_left [31:0] $end
$var wire 32 * sample_right [31:0] $end
$var wire 4 + sample_size [3:0] $end
$var wire 1 ( start $end
$var wire 1 ! word_select $end
$var reg 8 , bit_counter_left [7:0] $end
$var reg 8 - bit_counter_right [7:0] $end
$var reg 1 . busy_left $end
$var reg 1 / busy_right $end
$var reg 1 0 clk_out $end
$var reg 8 1 counter_size [7:0] $end
$var reg 1 2 current_out $end
$var reg 1 " data_out $end
$var reg 4 3 next_state [3:0] $end
$var reg 8 4 sample_left_r [7:0] $end
$var reg 8 5 sample_right_r [7:0] $end
$var reg 4 6 state [3:0] $end
$upscope $end
$upscope $end
$enddefinitions $end
#0
$dumpvars
bx 6
bx 5
bx 4
b0 3
x2
bx 1
x0
x/
x.
bx -
bx ,
b0 +
b10010001 *
b10010001 )
0(
b0 '
b10010001 &
b10010001 %
0$
0#
x"
x!
$end
#1000
1$
#2000
b1000 1
b0 6
0!
02
00
0"
0.
0/
b0 5
b0 4
1#
#4000
0#
0$
#5000
b1 3
1(
#6000
b11 3
b1 6
1#
#8000
0#
0(
#10000
b11 6
b1001 ,
b1001 -
b10010001 5
b10010001 4
1#
#12000
0#
#14000
b1001000 4
1"
b1000 ,
1#
#16000
0#
#18000
b100100 4
0"
b111 ,
1#
#20000
0#
#22000
b10010 4
b110 ,
1#
#24000
0#
#26000
b1001 4
b101 ,
1#
#28000
0#
#30000
b100 4
1"
b100 ,
1#
#32000
0#
#34000
b10 4
0"
b11 ,
1#
#36000
0#
#38000
b1 4
b10 ,
1#
#40000
0#
#42000
b0 4
1"
b1 ,
1#
#44000
0#
#46000
0"
b0 ,
1#
#48000
0#
#50000
b1000 ,
1!
12
1#
#52000
0#
#54000
b1001000 5
1"
b1000 -
1#
#56000
0#
#58000
b100100 5
0"
b111 -
1#
#60000
0#
#62000
b10010 5
b110 -
1#
#64000
0#
#66000
b1001 5
b101 -
1#
#68000
0#
#70000
b100 5
1"
b100 -
1#
#72000
0#
#74000
b10 5
0"
b11 -
1#
#76000
0#
#78000
b1 5
b10 -
1#
#80000
0#
#82000
b0 5
1"
b1 -
1#
#84000
0#
#86000
0"
b0 -
1#
#88000
0#
#90000
b1000 -
0!
02
1#
#92000
0#
#94000
b111 ,
1#
#96000
0#
#98000
b110 ,
1#
#100000
0#
#102000
b101 ,
1#
#104000
0#
#106000
b100 ,
1#
#108000
0#
#110000
b11 ,
1#
#112000
0#
#114000
b10 ,
1#
#116000
0#
#118000
b1 ,
1#
#120000
0#
#122000
b0 ,
1#
#124000
0#
#126000
b1000 ,
1!
12
1#
#128000
0#
#130000
b111 -
1#
#132000
0#
#134000
b110 -
1#
#136000
0#
#138000
b101 -
1#
#140000
0#
#142000
b100 -
1#
#144000
0#
#146000
b11 -
1#
#148000
0#
#150000
b10 -
1#
#152000
0#
#154000
b1 -
1#
#156000
0#
#158000
b0 -
1#
#160000
0#
#162000
b1000 -
0!
02
1#
#164000
0#
#166000
b111 ,
1#
#168000
0#
#170000
b110 ,
1#
#172000
0#
#174000
b101 ,
1#
#176000
0#
#178000
b100 ,
1#
#180000
0#
#182000
b11 ,
1#
#184000
0#
#186000
b10 ,
1#
#188000
0#
#190000
b1 ,
1#
#192000
0#
#194000
b0 ,
1#
#196000
0#
#198000
b1000 ,
1!
12
1#
#200000
0#
#202000
b111 -
1#
#204000
0#
#206000
b110 -
1#
#208000
0#
#210000
b101 -
1#
#212000
0#
#214000
b100 -
1#
#216000
0#
#218000
b11 -
1#
#220000
0#
#222000
b10 -
1#
#224000
0#
#226000
b1 -
1#
#228000
0#
#230000
b0 -
1#
#232000
0#
#234000
b1000 -
0!
02
1#
#236000
0#
#238000
b111 ,
1#
#240000
0#
#242000
b110 ,
1#
#244000
0#
#246000
b101 ,
1#
#248000
0#
#250000
b100 ,
1#
#252000
0#
#254000
b11 ,
1#
#256000
0#
#258000
b10 ,
1#
#260000
0#
#262000
b1 ,
1#
#264000
0#
#266000
b0 ,
1#
#268000
0#
#270000
b1000 ,
1!
12
1#
#272000
0#
#274000
b111 -
1#
#276000
0#
#278000
b110 -
1#
#280000
0#
#282000
b101 -
1#
#284000
0#
#286000
b100 -
1#
#288000
0#
#290000
b11 -
1#
#292000
0#
#294000
b10 -
1#
#296000
0#
#298000
b1 -
1#
#300000
0#
#302000
b0 -
1#
#304000
0#
#306000
b1000 -
0!
02
1#
#308000
0#
#310000
b111 ,
1#
#312000
0#
#314000
b110 ,
1#
#316000
0#
#318000
b101 ,
1#
#320000
0#
#322000
b100 ,
1#
#324000
0#
#326000
b11 ,
1#
#328000
0#
#330000
b10 ,
1#
#332000
0#
#334000
b1 ,
1#
#336000
0#
#338000
b0 ,
1#
#340000
0#
#342000
b1000 ,
1!
12
1#
#344000
0#
#346000
b111 -
1#
#348000
0#
#350000
b110 -
1#
#352000
0#
#354000
b101 -
1#
#356000
0#
#358000
b100 -
1#
#360000
0#
#362000
b11 -
1#
#364000
0#
#366000
b10 -
1#
#368000
0#
#370000
b1 -
1#
#372000
0#
#374000
b0 -
1#
#376000
0#
#378000
b1000 -
0!
02
1#
#380000
0#
#382000
b111 ,
1#
#384000
0#
#386000
b110 ,
1#
#388000
0#
#390000
b101 ,
1#
#392000
0#
#394000
b100 ,
1#
#396000
0#
#398000
b11 ,
1#
#400000
0#
#402000
b10 ,
1#
#404000
0#
#406000
b1 ,
1#
#408000
0#
#410000
b0 ,
1#
#412000
0#
#414000
b1000 ,
1!
12
1#
#416000
0#
#418000
b111 -
1#
#420000
0#
#422000
b110 -
1#
#424000
0#
#426000
b101 -
1#
#428000
0#
#430000
b100 -
1#
#432000
0#
#434000
b11 -
1#
#436000
0#
#438000
b10 -
1#
#440000
0#
#442000
b1 -
1#
#444000
0#
#446000
b0 -
1#
#448000
0#
#450000
b1000 -
0!
02
1#
#452000
0#
#454000
b111 ,
1#
#456000
0#
#458000
b110 ,
1#
#460000
0#
#462000
b101 ,
1#
#464000
0#
#466000
b100 ,
1#
#468000
0#
#470000
b11 ,
1#
#472000
0#
#474000
b10 ,
1#
#476000
0#
#478000
b1 ,
1#
#480000
0#
#482000
b0 ,
1#
#484000
0#
#486000
b1000 ,
1!
12
1#
#488000
0#
#490000
b111 -
1#
#492000
0#
#494000
b110 -
1#
#496000
0#
#498000
b101 -
1#
#500000
0#
#502000
b100 -
1#
#504000
0#
#506000
b11 -
1#
#508000
0#
#510000
b10 -
1#
#512000
0#
#514000
b1 -
1#
#516000
0#
#518000
b0 -
1#
#520000
0#
#522000
b1000 -
0!
02
1#
#524000
0#
#526000
b111 ,
1#
#528000
0#
#530000
b110 ,
1#
#532000
0#
#534000
b101 ,
1#
#536000
0#
#538000
b100 ,
1#
#540000
0#
#542000
b11 ,
1#
#544000
0#
#546000
b10 ,
1#
#548000
0#
#550000
b1 ,
1#
#552000
0#
#554000
b0 ,
1#
#556000
0#
#558000
b1000 ,
1!
12
1#
#560000
0#
#562000
b111 -
1#
#564000
0#
#566000
b110 -
1#
#568000
0#
#570000
b101 -
1#
#572000
0#
#574000
b100 -
1#
#576000
0#
#578000
b11 -
1#
#580000
0#
#582000
b10 -
1#
#584000
0#
#586000
b1 -
1#
#588000
0#
#590000
b0 -
1#
#592000
0#
#594000
b1000 -
0!
02
1#
#596000
0#
#598000
b111 ,
1#
#600000
0#
#602000
b110 ,
1#
#604000
0#
#606000
b101 ,
1#
#608000
0#
#610000
b100 ,
1#
#612000
0#
#614000
b11 ,
1#
#616000
0#
#618000
b10 ,
1#
#620000
0#
#622000
b1 ,
1#
#624000
0#
#626000
b0 ,
1#
#628000
0#
#630000
b1000 ,
1!
12
1#
#632000
0#
#634000
b111 -
1#
#636000
0#
#638000
b110 -
1#
#640000
0#
#642000
b101 -
1#
#644000
0#
#646000
b100 -
1#
#648000
0#
#650000
b11 -
1#
#652000
0#
#654000
b10 -
1#
#656000
0#
#658000
b1 -
1#
#660000
0#
#662000
b0 -
1#
#664000
0#
#666000
b1000 -
0!
02
1#
#668000
0#
#670000
b111 ,
1#
#672000
0#
#674000
b110 ,
1#
#676000
0#
#678000
b101 ,
1#
#680000
0#
#682000
b100 ,
1#
#684000
0#
#686000
b11 ,
1#
#688000
0#
#690000
b10 ,
1#
#692000
0#
#694000
b1 ,
1#
#696000
0#
#698000
b0 ,
1#
#700000
0#
#702000
b1000 ,
1!
12
1#
#704000
0#
#706000
b111 -
1#
#708000
0#
#710000
b110 -
1#
#712000
0#
#714000
b101 -
1#
#716000
0#
#718000
b100 -
1#
#720000
0#
#722000
b11 -
1#
#724000
0#
#726000
b10 -
1#
#728000
0#
#730000
b1 -
1#
#732000
0#
#734000
b0 -
1#
#736000
0#
#738000
b1000 -
0!
02
1#
#740000
0#
#742000
b111 ,
1#
#744000
0#
#746000
b110 ,
1#
#748000
0#
#750000
b101 ,
1#
#752000
0#
#754000
b100 ,
1#
#756000
0#
#758000
b11 ,
1#
#760000
0#
#762000
b10 ,
1#
#764000
0#
#766000
b1 ,
1#
#768000
0#
#770000
b0 ,
1#
#772000
0#
#774000
b1000 ,
1!
12
1#
#776000
0#
#778000
b111 -
1#
#780000
0#
#782000
b110 -
1#
#784000
0#
#786000
b101 -
1#
#788000
0#
#790000
b100 -
1#
#792000
0#
#794000
b11 -
1#
#796000
0#
#798000
b10 -
1#
#800000
0#
#802000
b1 -
1#
#804000
0#
#806000
b0 -
1#
#808000
0#
#810000
b1000 -
0!
02
1#
#812000
0#
#814000
b111 ,
1#
#816000
0#
#818000
b110 ,
1#
#820000
0#
#822000
b101 ,
1#
#824000
0#
#826000
b100 ,
1#
#828000
0#
#830000
b11 ,
1#
#832000
0#
#834000
b10 ,
1#
#836000
0#
#838000
b1 ,
1#
#840000
0#
#842000
b0 ,
1#
#844000
0#
#846000
b1000 ,
1!
12
1#
#848000
0#
#850000
b111 -
1#
#852000
0#
#854000
b110 -
1#
#856000
0#
#858000
b101 -
1#
#860000
0#
#862000
b100 -
1#
#864000
0#
#866000
b11 -
1#
#868000
0#
#870000
b10 -
1#
#872000
0#
#874000
b1 -
1#
#876000
0#
#878000
b0 -
1#
#880000
0#
#882000
b1000 -
0!
02
1#
#884000
0#
#886000
b111 ,
1#
#888000
0#
#890000
b110 ,
1#
#892000
0#
#894000
b101 ,
1#
#896000
0#
#898000
b100 ,
1#
#900000
0#
#902000
b11 ,
1#
#904000
0#
#906000
b10 ,
1#
#908000
0#
#910000
b1 ,
1#
#912000
0#
#914000
b0 ,
1#
#916000
0#
#918000
b1000 ,
1!
12
1#
#920000
0#
#922000
b111 -
1#
#924000
0#
#926000
b110 -
1#
#928000
0#
#930000
b101 -
1#
#932000
0#
#934000
b100 -
1#
#936000
0#
#938000
b11 -
1#
#940000
0#
#942000
b10 -
1#
#944000
0#
#946000
b1 -
1#
#948000
0#
#950000
b0 -
1#
#952000
0#
#954000
b1000 -
0!
02
1#
#956000
0#
#958000
b111 ,
1#
#960000
0#
#962000
b110 ,
1#
#964000
0#
#966000
b101 ,
1#
#968000
0#
#970000
b100 ,
1#
#972000
0#
#974000
b11 ,
1#
#976000
0#
#978000
b10 ,
1#
#980000
0#
#982000
b1 ,
1#
#984000
0#
#986000
b0 ,
1#
#988000
0#
#990000
b1000 ,
1!
12
1#
#992000
0#
#994000
b111 -
1#
#996000
0#
#998000
b110 -
1#
#1000000
0#
#1002000
b101 -
1#
#1004000
0#
#1006000
b100 -
1#
#1008000
0#
#1010000
b11 -
1#
#1012000
0#
#1014000
b10 -
1#
#1016000
0#
#1018000
b1 -
1#
#1020000
0#
#1022000
b0 -
1#
#1024000
0#
#1026000
b1000 -
0!
02
1#
#1028000
0#
#1030000
b111 ,
1#
#1032000
0#
#1034000
b110 ,
1#
#1036000
0#
#1038000
b101 ,
1#
#1040000
0#
#1042000
b100 ,
1#
#1044000
0#
#1046000
b11 ,
1#
#1048000
0#
#1050000
b10 ,
1#
#1052000
0#
#1054000
b1 ,
1#
#1056000
0#
#1058000
b0 ,
1#
#1060000
0#
#1062000
b1000 ,
1!
12
1#
#1064000
0#
#1066000
b111 -
1#
#1068000
0#
#1070000
b110 -
1#
#1072000
0#
#1074000
b101 -
1#
#1076000
0#
#1078000
b100 -
1#
#1080000
0#
#1082000
b11 -
1#
#1084000
0#
#1086000
b10 -
1#
#1088000
0#
#1090000
b1 -
1#
#1092000
0#
#1094000
b0 -
1#
#1096000
0#
#1098000
b1000 -
0!
02
1#
#1100000
0#
#1102000
b111 ,
1#
#1104000
0#
#1106000
b110 ,
1#
#1108000
0#
#1110000
b101 ,
1#
#1112000
0#
#1114000
b100 ,
1#
#1116000
0#
#1118000
b11 ,
1#
#1120000
0#
#1122000
b10 ,
1#
#1124000
0#
#1126000
b1 ,
1#
#1128000
0#
#1130000
b0 ,
1#
#1132000
0#
#1134000
b1000 ,
1!
12
1#
#1136000
0#
#1138000
b111 -
1#
#1140000
0#
#1142000
b110 -
1#
#1144000
0#
#1146000
b101 -
1#
#1148000
0#
#1150000
b100 -
1#
#1152000
0#
#1154000
b11 -
1#
#1156000
0#
#1158000
b10 -
1#
#1160000
0#
#1162000
b1 -
1#
#1164000
0#
#1166000
b0 -
1#
#1168000
0#
#1170000
b1000 -
0!
02
1#
#1172000
0#
#1174000
b111 ,
1#
#1176000
0#
#1178000
b110 ,
1#
#1180000
0#
#1182000
b101 ,
1#
#1184000
0#
#1186000
b100 ,
1#
#1188000
0#
#1190000
b11 ,
1#
#1192000
0#
#1194000
b10 ,
1#
#1196000
0#
#1198000
b1 ,
1#
#1200000
0#
#1202000
b0 ,
1#
#1204000
0#
#1206000
b1000 ,
1!
12
1#
#1208000
0#
#1210000
b111 -
1#
#1212000
0#
#1214000
b110 -
1#
#1216000
0#
#1218000
b101 -
1#
#1220000
0#
#1222000
b100 -
1#
#1224000
0#
#1226000
b11 -
1#
#1228000
0#
#1230000
b10 -
1#
#1232000
0#
#1234000
b1 -
1#
#1236000
0#
#1238000
b0 -
1#
#1240000
0#
#1242000
b1000 -
0!
02
1#
#1244000
0#
#1246000
b111 ,
1#
#1248000
0#
#1250000
b110 ,
1#
#1252000
0#
#1254000
b101 ,
1#
#1256000
0#
#1258000
b100 ,
1#
#1260000
0#
#1262000
b11 ,
1#
#1264000
0#
#1266000
b10 ,
1#
#1268000
0#
#1270000
b1 ,
1#
#1272000
0#
#1274000
b0 ,
1#
#1276000
0#
#1278000
b1000 ,
1!
12
1#
#1280000
0#
#1282000
b111 -
1#
#1284000
0#
#1286000
b110 -
1#
#1288000
0#
#1290000
b101 -
1#
#1292000
0#
#1294000
b100 -
1#
#1296000
0#
#1298000
b11 -
1#
#1300000
0#
#1302000
b10 -
1#
#1304000
0#
#1306000
b1 -
1#
#1308000
0#
#1310000
b0 -
1#
#1312000
0#
#1314000
b1000 -
0!
02
1#
#1316000
0#
#1318000
b111 ,
1#
#1320000
0#
#1322000
b110 ,
1#
#1324000
0#
#1326000
b101 ,
1#
#1328000
0#
#1330000
b100 ,
1#
#1332000
0#
#1334000
b11 ,
1#
#1336000
0#
#1338000
b10 ,
1#
#1340000
0#
#1342000
b1 ,
1#
#1344000
0#
#1346000
b0 ,
1#
#1348000
0#
#1350000
b1000 ,
1!
12
1#
#1352000
0#
#1354000
b111 -
1#
#1356000
0#
#1358000
b110 -
1#
#1360000
0#
#1362000
b101 -
1#
#1364000
0#
#1366000
b100 -
1#
#1368000
0#
#1370000
b11 -
1#
#1372000
0#
#1374000
b10 -
1#
#1376000
0#
#1378000
b1 -
1#
#1380000
0#
#1382000
b0 -
1#
#1384000
0#
#1386000
b1000 -
0!
02
1#
#1388000
0#
#1390000
b111 ,
1#
#1392000
0#
#1394000
b110 ,
1#
#1396000
0#
#1398000
b101 ,
1#
#1400000
0#
#1402000
b100 ,
1#
#1404000
0#
#1406000
b11 ,
1#
#1408000
0#
#1410000
b10 ,
1#
#1412000
0#
#1414000
b1 ,
1#
#1416000
0#
#1418000
b0 ,
1#
#1420000
0#
#1422000
b1000 ,
1!
12
1#
#1424000
0#
#1426000
b111 -
1#
#1428000
0#
#1430000
b110 -
1#
#1432000
0#
#1434000
b101 -
1#
#1436000
0#
#1438000
b100 -
1#
#1440000
0#
#1442000
b11 -
1#
#1444000
0#
#1446000
b10 -
1#
#1448000
0#
#1450000
b1 -
1#
#1452000
0#
#1454000
b0 -
1#
#1456000
0#
#1458000
b1000 -
0!
02
1#
#1460000
0#
#1462000
b111 ,
1#
#1464000
0#
#1466000
b110 ,
1#
#1468000
0#
#1470000
b101 ,
1#
#1472000
0#
#1474000
b100 ,
1#
#1476000
0#
#1478000
b11 ,
1#
#1480000
0#
#1482000
b10 ,
1#
#1484000
0#
#1486000
b1 ,
1#
#1488000
0#
#1490000
b0 ,
1#
#1492000
0#
#1494000
b1000 ,
1!
12
1#
#1496000
0#
#1498000
b111 -
1#
#1500000
0#
#1502000
b110 -
1#
#1504000
0#
#1506000
b101 -
1#
#1508000
0#
#1510000
b100 -
1#
#1512000
0#
#1514000
b11 -
1#
#1516000
0#
#1518000
b10 -
1#
#1520000
0#
#1522000
b1 -
1#
#1524000
0#
#1526000
b0 -
1#
#1528000
0#
#1530000
b1000 -
0!
02
1#
#1532000
0#
#1534000
b111 ,
1#
#1536000
0#
#1538000
b110 ,
1#
#1540000
0#
#1542000
b101 ,
1#
#1544000
0#
#1546000
b100 ,
1#
#1548000
0#
#1550000
b11 ,
1#
#1552000
0#
#1554000
b10 ,
1#
#1556000
0#
#1558000
b1 ,
1#
#1560000
0#
#1562000
b0 ,
1#
#1564000
0#
#1566000
b1000 ,
1!
12
1#
#1568000
0#
#1570000
b111 -
1#
#1572000
0#
#1574000
b110 -
1#
#1576000
0#
#1578000
b101 -
1#
#1580000
0#
#1582000
b100 -
1#
#1584000
0#
#1586000
b11 -
1#
#1588000
0#
#1590000
b10 -
1#
#1592000
0#
#1594000
b1 -
1#
#1596000
0#
#1598000
b0 -
1#
#1600000
0#
#1602000
b1000 -
0!
02
1#
#1604000
0#
#1606000
b111 ,
1#
#1608000
0#
#1610000
b110 ,
1#
#1612000
0#
#1614000
b101 ,
1#
#1616000
0#
#1618000
b100 ,
1#
#1620000
0#
#1622000
b11 ,
1#
#1624000
0#
#1626000
b10 ,
1#
#1628000
0#
#1630000
b1 ,
1#
#1632000
0#
#1634000
b0 ,
1#
#1636000
0#
#1638000
b1000 ,
1!
12
1#
#1640000
0#
#1642000
b111 -
1#
#1644000
0#
#1646000
b110 -
1#
#1648000
0#
#1650000
b101 -
1#
#1652000
0#
#1654000
b100 -
1#
#1656000
0#
#1658000
b11 -
1#
#1660000
0#
#1662000
b10 -
1#
#1664000
0#
#1666000
b1 -
1#
#1668000
0#
#1670000
b0 -
1#
#1672000
0#
#1674000
b1000 -
0!
02
1#
#1676000
0#
#1678000
b111 ,
1#
#1680000
0#
#1682000
b110 ,
1#
#1684000
0#
#1686000
b101 ,
1#
#1688000
0#
#1690000
b100 ,
1#
#1692000
0#
#1694000
b11 ,
1#
#1696000
0#
#1698000
b10 ,
1#
#1700000
0#
#1702000
b1 ,
1#
#1704000
0#
#1706000
b0 ,
1#
#1708000
0#
#1710000
b1000 ,
1!
12
1#
#1712000
0#
#1714000
b111 -
1#
#1716000
0#
#1718000
b110 -
1#
#1720000
0#
#1722000
b101 -
1#
#1724000
0#
#1726000
b100 -
1#
#1728000
0#
#1730000
b11 -
1#
#1732000
0#
#1734000
b10 -
1#
#1736000
0#
#1738000
b1 -
1#
#1740000
0#
#1742000
b0 -
1#
#1744000
0#
#1746000
b1000 -
0!
02
1#
#1748000
0#
#1750000
b111 ,
1#
#1752000
0#
#1754000
b110 ,
1#
#1756000
0#
#1758000
b101 ,
1#
#1760000
0#
#1762000
b100 ,
1#
#1764000
0#
#1766000
b11 ,
1#
#1768000
0#
#1770000
b10 ,
1#
#1772000
0#
#1774000
b1 ,
1#
#1776000
0#
#1778000
b0 ,
1#
#1780000
0#
#1782000
b1000 ,
1!
12
1#
#1784000
0#
#1786000
b111 -
1#
#1788000
0#
#1790000
b110 -
1#
#1792000
0#
#1794000
b101 -
1#
#1796000
0#
#1798000
b100 -
1#
#1800000
0#
#1802000
b11 -
1#
#1804000
0#
#1806000
b10 -
1#
#1808000
0#
#1810000
b1 -
1#
#1812000
0#
#1814000
b0 -
1#
#1816000
0#
#1818000
b1000 -
0!
02
1#
#1820000
0#
#1822000
b111 ,
1#
#1824000
0#
#1826000
b110 ,
1#
#1828000
0#
#1830000
b101 ,
1#
#1832000
0#
#1834000
b100 ,
1#
#1836000
0#
#1838000
b11 ,
1#
#1840000
0#
#1842000
b10 ,
1#
#1844000
0#
#1846000
b1 ,
1#
#1848000
0#
#1850000
b0 ,
1#
#1852000
0#
#1854000
b1000 ,
1!
12
1#
#1856000
0#
#1858000
b111 -
1#
#1860000
0#
#1862000
b110 -
1#
#1864000
0#
#1866000
b101 -
1#
#1868000
0#
#1870000
b100 -
1#
#1872000
0#
#1874000
b11 -
1#
#1876000
0#
#1878000
b10 -
1#
#1880000
0#
#1882000
b1 -
1#
#1884000
0#
#1886000
b0 -
1#
#1888000
0#
#1890000
b1000 -
0!
02
1#
#1892000
0#
#1894000
b111 ,
1#
#1896000
0#
#1898000
b110 ,
1#
#1900000
0#
#1902000
b101 ,
1#
#1904000
0#
#1906000
b100 ,
1#
#1908000
0#
#1910000
b11 ,
1#
#1912000
0#
#1914000
b10 ,
1#
#1916000
0#
#1918000
b1 ,
1#
#1920000
0#
#1922000
b0 ,
1#
#1924000
0#
#1926000
b1000 ,
1!
12
1#
#1928000
0#
#1930000
b111 -
1#
#1932000
0#
#1934000
b110 -
1#
#1936000
0#
#1938000
b101 -
1#
#1940000
0#
#1942000
b100 -
1#
#1944000
0#
#1946000
b11 -
1#
#1948000
0#
#1950000
b10 -
1#
#1952000
0#
#1954000
b1 -
1#
#1956000
0#
#1958000
b0 -
1#
#1960000
0#
#1962000
b1000 -
0!
02
1#
#1964000
0#
#1966000
b111 ,
1#
#1968000
0#
#1970000
b110 ,
1#
#1972000
0#
#1974000
b101 ,
1#
#1976000
0#
#1978000
b100 ,
1#
#1980000
0#
#1982000
b11 ,
1#
#1984000
0#
#1986000
b10 ,
1#
#1988000
0#
#1990000
b1 ,
1#
#1992000
0#
#1994000
b0 ,
1#
#1996000
0#
#1998000
b1000 ,
1!
12
1#
#2000000
0#
#2002000
b111 -
1#
#2004000
0#
#2006000
b110 -
1#
#2008000
0#
#2010000
b101 -
1#
#2012000
0#
#2014000
b100 -
1#
#2016000
0#
#2018000
b11 -
1#
#2020000
0#
#2022000
b10 -
1#
#2024000
0#
#2026000
b1 -
1#
#2028000
0#
#2030000
b0 -
1#
#2032000
0#
#2034000
b1000 -
0!
02
1#
#2036000
0#
#2038000
b111 ,
1#
#2040000
0#
#2042000
b110 ,
1#
#2044000
0#
#2046000
b101 ,
1#
#2048000
0#
#2050000
b100 ,
1#
#2052000
0#
#2054000
b11 ,
1#
#2056000
0#
#2058000
b10 ,
1#
#2060000
0#
#2062000
b1 ,
1#
#2064000
0#
#2066000
b0 ,
1#
#2068000
0#
#2070000
b1000 ,
1!
12
1#
#2072000
0#
#2074000
b111 -
1#
#2076000
0#
#2078000
b110 -
1#
#2080000
0#
#2082000
b101 -
1#
#2084000
0#
#2086000
b100 -
1#
#2088000
0#
#2090000
b11 -
1#
#2092000
0#
#2094000
b10 -
1#
#2096000
0#
#2098000
b1 -
1#
#2100000
0#
#2102000
b0 -
1#
#2104000
0#
#2106000
b1000 -
0!
02
1#
#2108000
0#
#2110000
b111 ,
1#
#2112000
0#
#2114000
b110 ,
1#
#2116000
0#
#2118000
b101 ,
1#
#2120000
0#
#2122000
b100 ,
1#
#2124000
0#
#2126000
b11 ,
1#
#2128000
0#
#2130000
b10 ,
1#
#2132000
0#
#2134000
b1 ,
1#
#2136000
0#
#2138000
b0 ,
1#
#2140000
0#
#2142000
b1000 ,
1!
12
1#
#2144000
0#
#2146000
b111 -
1#
#2148000
0#
#2150000
b110 -
1#
#2152000
0#
#2154000
b101 -
1#
#2156000
0#
#2158000
b100 -
1#
#2160000
0#
#2162000
b11 -
1#
#2164000
0#
#2166000
b10 -
1#
#2168000
0#
#2170000
b1 -
1#
#2172000
0#
#2174000
b0 -
1#
#2176000
0#
#2178000
b1000 -
0!
02
1#
#2180000
0#
#2182000
b111 ,
1#
#2184000
0#
#2186000
b110 ,
1#
#2188000
0#
#2190000
b101 ,
1#
#2192000
0#
#2194000
b100 ,
1#
#2196000
0#
#2198000
b11 ,
1#
#2200000
0#
#2202000
b10 ,
1#
#2204000
0#
#2206000
b1 ,
1#
#2208000
0#
#2210000
b0 ,
1#
#2212000
0#
#2214000
b1000 ,
1!
12
1#
#2216000
0#
#2218000
b111 -
1#
#2220000
0#
#2222000
b110 -
1#
#2224000
0#
#2226000
b101 -
1#
#2228000
0#
#2230000
b100 -
1#
#2232000
0#
#2234000
b11 -
1#
#2236000
0#
#2238000
b10 -
1#
#2240000
0#
#2242000
b1 -
1#
#2244000
0#
#2246000
b0 -
1#
#2248000
0#
#2250000
b1000 -
0!
02
1#
#2252000
0#
#2254000
b111 ,
1#
#2256000
0#
#2258000
b110 ,
1#
#2260000
0#
#2262000
b101 ,
1#
#2264000
0#
#2266000
b100 ,
1#
#2268000
0#
#2270000
b11 ,
1#
#2272000
0#
#2274000
b10 ,
1#
#2276000
0#
#2278000
b1 ,
1#
#2280000
0#
#2282000
b0 ,
1#
