src/sample_processor.v
module sample_processor (
    input clk,
    input rst,
    input [7:0] data_in,
    output [31:0] data_out,
    input [3:0] sample_size,
    input data_available,
    output reg data_ready
);
    parameter S_8BIT=0, S_12BIT=1, S_16BIT=3, S_24BIT=4, S_32BIT=5;
    parameter S_BLOCK_8BIT=1, S_BLOCK_12BIT=2, S_BLOCK_16BIT=2, S_BLOCK_24BIT=3, S_BLOCK_32BIT=4;
    parameter S_MASK_8BIT=32'hFF, S_MASK_12BIT=32'hFFF, S_MASK_16BIT=32'hFFFF, S_MASK_24BIT=32'hFFFFF, S_MASK_32BIT=32'hFFFFFFFF;

    reg [3:0] current_block_n;
    reg [7:0] sample_blocks [3:0];
    reg [3:0] n_blocks_per_sample;
    reg [31:0] sample_mask;

    assign data_out = {sample_blocks[3], sample_blocks[2], sample_blocks[1], sample_blocks[0]} & sample_mask;

    always @(*) begin
		case(sample_size)
			S_8BIT : n_blocks_per_sample <= S_BLOCK_8BIT;
			S_12BIT : n_blocks_per_sample <= S_BLOCK_12BIT;
			S_16BIT : n_blocks_per_sample <= S_BLOCK_16BIT;
			S_24BIT : n_blocks_per_sample <= S_BLOCK_24BIT;
			S_32BIT : n_blocks_per_sample <= S_BLOCK_32BIT;
		endcase
	end

    always @(*) begin
		case(sample_size)
			S_8BIT : sample_mask <= S_MASK_8BIT;
			S_12BIT : sample_mask <= S_MASK_12BIT;
			S_16BIT : sample_mask <= S_MASK_16BIT;
			S_24BIT : sample_mask <= S_MASK_24BIT;
			S_32BIT : sample_mask <= S_MASK_32BIT;
		endcase
	end


    always @ (posedge clk) begin
        if(rst) begin
            data_ready <= 0;
            current_block_n <= 0;
            sample_blocks[0] = 0;
            sample_blocks[1] = 0;
            sample_blocks[2] = 0;
            sample_blocks[3] = 0;
        end
        else if(data_available == 0) begin
            if(current_block_n == n_blocks_per_sample) begin
                data_ready <= 1;
            end
            else begin
                sample_blocks[current_block_n] <= data_in;
                current_block_n <= current_block_n + 1;
            end
        end

    end

 

endmodule

//dff <= {dff[4-2:0], dff[3] ^ dff[2] ^ scan_in};

src/sample_processor_tb.v
`timescale 1ns / 1ps

module I2S_shift_register_tb;
	parameter S_8BIT=0, S_12BIT=1, S_16BIT=3, S_32BIT=4;
	parameter BLOCK0 = 8'hAA;
	parameter BLOCK1 = 8'hFF;
	parameter SAMPLE_SIZE_VALUE = S_12BIT;

	reg CLK;
	reg START;
	reg RST;
    reg [7:0] DATA_IN;
    reg SAMPLE_SIZE;
	wire DATA_READY;
    wire [31:0] DATA_OUT;
    

	sample_processor uut (
    .clk(CLK),
    .rst(RST),
    .data_in(DATA_IN),
    .data_out(DATA_OUT),
    .sample_size(SAMPLE_SIZE),
    .data_available(START),
    .data_ready(DATA_READY)
);

	
	initial begin
		$dumpfile("sample_processor_test.vcd");
		$dumpvars();
		CLK = 0;
		START = 1;
		RST = 0;
		DATA_IN = BLOCK0;
        SAMPLE_SIZE = S_12BIT;
		
	end
	
	initial begin
		wait(!CLK);
		#1
		RST = 1;
		#3
		RST = 0;
		
		wait(!CLK);
		#1
		START = 0;
		#3
		START = 1;
        
        DATA_IN = BLOCK1;
        #10

        wait(!CLK);
		#1
		START = 0;
		#3
		START = 1;


		
	end
	
	
	
	initial begin
        #3000 $finish;
    end

    always
        #2  CLK =  ! CLK;

endmodule

src/sample_processor_test.vcd
$date
	Wed Aug 26 19:52:56 2020
$end
$version
	Icarus Verilog
$end
$timescale
	1ps
$end
$scope module I2S_shift_register_tb $end
$var wire 1 ! DATA_READY $end
$var wire 32 " DATA_OUT [31:0] $end
$var reg 1 # CLK $end
$var reg 8 $ DATA_IN [7:0] $end
$var reg 1 % RST $end
$var reg 1 & SAMPLE_SIZE $end
$var reg 1 ' START $end
$scope module uut $end
$var wire 1 # clk $end
$var wire 1 ' data_available $end
$var wire 8 ( data_in [7:0] $end
$var wire 32 ) data_out [31:0] $end
$var wire 1 % rst $end
$var wire 4 * sample_size [3:0] $end
$var reg 4 + current_block_n [3:0] $end
$var reg 1 ! data_ready $end
$var reg 4 , n_blocks_per_sample [3:0] $end
$var reg 32 - sample_mask [31:0] $end
$upscope $end
$upscope $end
$enddefinitions $end
#0
$dumpvars
b111111111111 -
b10 ,
bx +
b1 *
b0xxxxxxxxxxxx )
b10101010 (
1'
1&
0%
b10101010 $
0#
b0xxxxxxxxxxxx "
x!
$end
#1000
1%
#2000
b0 +
0!
b0 "
b0 )
1#
#4000
0#
0%
#5000
b10101010 "
b10101010 )
b1 +
0'
#6000
1#
#8000
0#
b11111111 $
b11111111 (
1'
#10000
1#
#12000
0#
#14000
1#
#16000
0#
#18000
1#
#19000
b111110101010 "
b111110101010 )
b10 +
0'
#20000
0#
#22000
1#
1'
